Metadata-Version: 1.2
Name: aetacsdcscsdcawaca
Version: 1.0.0
Summary: A print test for PyPI
Home-page: https://www.python.org/
Author: lingshiyinzi
Author-email: 294594605@qq.com
License: MIT
Keywords: ga nn
Platform: UNKNOWN
Requires-Python: >=3
